IA23005UNO/__init__.py
IA23005UNO/metodos.py
ia23005uno-0.1.0.dist-info/licenses/LICENSE
ia23005uno-0.1.0.dist-info/METADATA
ia23005uno-0.1.0.dist-info/WHEEL
ia23005uno-0.1.0.dist-info/top_level.txt
ia23005uno-0.1.0.dist-info/RECORD
