Metadata-Version: 2.4
Name: IA23005UNO
Version: 0.1.0
Summary: Librería para resolver sistemas de ecuaciones lineales y no lineales
Home-page: https://github.com/RubenIglesias1F20/IA23005UNO
Download-URL: 
Author: Rubén Iglesias IA23005
Author-email: rubenedgardo70080503@gmail.com
License: MIT
Classifier: Programming Language :: Python :: 3
Classifier: License :: OSI Approved :: MIT License
Classifier: Operating System :: OS Independent
Requires-Python: >=3.6
License-File: LICENSE
Requires-Dist: numpy>=1.20.0
Dynamic: author
Dynamic: author-email
Dynamic: classifier
Dynamic: description
Dynamic: description-content-type
Dynamic: home-page
Dynamic: license
Dynamic: license-file
Dynamic: requires-dist
Dynamic: requires-python
Dynamic: summary
